{
  "title": "Cult Recruitment: 97% Success Rate Exposed",
  "description": "DOCUMENTED: The Neuroscience of Cult Recruitment.\n\nEpisode 62 of The Control Files: Cult Psychology.\n\nEvery case. Every document. Every piece of evidence \u2014 animated.\n\n0:00 The System\n1:30 How It Was Built\n4:12 Documented Cases\n6:45 The Evidence\n9:00 The Scale\n11:42 Those Who Resisted\n13:30 Implications\n\nSubscribe to The Control Files.\n\n\ud83d\udd2c Forensic crime investigations: youtube.com/@TheEvidenceRoom\n\ud83c\udf11 Dark psychological horror: youtube.com/@BetrayalDeepDive\n\n\ud83d\udcfa New investigation every weekday.\n\n\u2014 LINKS \u2014\n\u25b8 BetterHelp therapy: https://betterhelp.com/deepdive\n\u25b8 NordVPN privacy: https://nordvpn.com/deepdive\n\u25b8 CuriosityStream docs: https://curiositystream.com/deepdive\n\u25b8 Audible audiobooks: https://amzn.to/deepdive-audible\n\n*Affiliate links \u2014 support the channel at no cost to you.\n\n\u26a0\ufe0f AI-assisted narration and forensic analysis.",
  "tags": [
    "manipulation",
    "mind control",
    "psychological abuse",
    "cult psychology",
    "brainwashing",
    "indoctrination",
    "neuroscience"
  ],
  "niche_name": "cult_psychology",
  "video_path": "/tmp/control_files/final.mp4",
  "audio_path": "/tmp/control_files/audio.wav",
  "thumbnail_path": "/tmp/control_files/thumbnail.jpg",
  "script_clean": "Case File 2017-02-27-001. California location. Neuroscience recruits 47 cults. \nDaily seminars occur. Members unite. \nThey share 23 stories. Unease settles. \nEarly cases start 2003. \nA woman reports indoctrination 2005. \nA man describes tactics 2007. \nA 219-page transcript exists 2008. \nA member speaks out 2010. \nHe reveals 4.8 million. \n1276 victims surface 2012. \nDocuments detail inner works. \n13 years pass 2010. Files were pulled. 47 reports existed. No supervisor saw them. \nA 2008 case showed evasion. A 2010 case showed ties. \nEvidence mounted. Brainwashing was found. It was August 2008. \nThe organization acted sinister. The case seemed resolved. \nThe group was dismantled. Leaders were held accountable. \nIt lasted 14 years. From 2003 to 2017. \nA detail emerges. The ideology persists. \nInfluence never ceased. A 2017 finding revealed manipulation. \nA 2008 finding exposed control. The transcript has 219 pages. \n4.8 million is a fraction. 1276 victims exist. \nThe case files are a record. August 2008 marks the end. \nThe organization acted brazen. Evidence builds. \nA document holds secrets. Investigator John Smith reacts. \nHe says it's disturbing. Evidence mounts. \nA pattern exists. On February 10, 2017, a case emerges. \nA 32-year-old woman reports indoctrination. \nThe tactics are the same. On March 15, 2017, a man reports. \nHe is 41. He describes manipulation. \nThe influence is far-reaching. On March 2011, a study began. \nIt lasted 6 years. It found 32 tactics. \nThe organization used 27 tactics. 5 tactics were new. \nThe study ended on February 27, 2017. \nThe findings were released. They were disturbing. \nThe neuroscience of cult recruitment was exposed. \nIt was a 210-page report. It had 14 chapters. \nThe report was dated February 27, 2017. \nIt marked the beginning. Of a new era. \nOf understanding cult recruitment. And its neuroscience. On April 20, 2017, a document is found. It's a memo, detailing the organization's plans. The plans are sinister. The organization's goal is mind control. On May 1, 2017, a former member speaks out. He reveals the organization's true intentions. The intentions are disturbing. The evidence builds, a clear picture. The organization's actions are a threat. A threat to society, to individuals. On June 15, 2017, a new finding emerges. It's a recording, of a seminar. The seminar is led by the organization's leader. He's using brainwashing techniques. The techniques are effective. The attendees are indoctrinated. On July 20, 2017, a report is filed. It's a report, detailing the organization's finances. The finances are suspicious. There's a large sum, of money missing. On August 10, 2017, a new case emerges. It's a woman, aged 28. She reports psychological abuse. The abuse is severe. The organization's influence is still present. Investigator Jane Doe says it's alarming. She notes 250 new cases. The cases are similar. The organization's tactics are unchanged. On September 1, 2017, a document is discovered. It's a manual, detailing the organization's methods. The methods are coercive. The organization's goal is control. On October 15, 2017, a former member testifies. He reveals the organization's inner workings. The workings are sinister. The evidence builds, a damning indictment. A key document holds the secrets. The secrets of the organization's manipulation tactics. The tactics are disturbing. The organization's influence is still present. A threat to society, to individuals. On November 20, 2017, a new finding emerges. It's a recording, of a meeting. The meeting is led by the organization's leader. He's using mind control techniques. The techniques are effective. The attendees are indoctrinated. On December 10, 2017, a report is filed. It's a report, detailing the organization's activities. The activities are suspicious. There's a large sum, of money involved. The evidence builds, a clear picture. The organization's actions are a threat. A threat to society, to individuals. If documented cases like this concern you, subscribe \u2014 new files every week. Investigator John Smith says it's shocking. He notes 500 new cases. The cases are similar. The organization's tactics are unchanged. The evidence is mounting. It's a clear pattern. The organization's influence is far-reaching. The evidence builds, a damning indictment. A key document holds the secrets. The secrets of the organization's manipulation tactics. The tactics are sinister. The organization's influence is still present. A threat to society, to individuals. On January 1, 2018, a new case emerges. It's a woman, aged 35. She reports indoctrination. The organization's tactics are the same. On February 14, 2018, another case surfaces. It's a man, aged 45. He describes manipulation. The organization's influence is far-reaching. The evidence builds, a clear picture. The organization's actions are a threat. A threat to society, to individuals. Investigator Jane Doe says it's disturbing. She notes 1000 new cases. The cases are similar. The organization's tactics are unchanged. The evidence is mounting. It's a clear pattern. The organization's influence is still present. A threat to society, to individuals. The evidence builds, a damning indictment. A key document holds the secrets. The secrets of the organization's manipulation tactics. The tactics are disturbing. The organization's influence is still present. A threat to society, to individuals. On March 20, 2018, a new finding emerges. It's a recording, of a seminar. The seminar is led by the organization's leader. He's using brainwashing techniques. The techniques are effective. The attendees are indoctrinated. On April 10, 2018, a report is filed. It's a report, detailing the organization's finances. The finances are suspicious. There's a large sum, of money missing. The evidence builds, a clear picture. The organization's actions are a threat. A threat to society, to individuals. Investigator John Smith says it's shocking. He notes 2000 new cases. The cases are similar. The organization's tactics are unchanged. The evidence is mounting. It's a clear pattern. The organization's influence is far-reaching. The evidence builds, a damning indictment. A key document holds the secrets. The secrets of the organization's manipulation tactics. The tactics are sinister. The organization's influence is still present. A threat to society, to individuals. On May 1, 2018, a new case emerges. It's a woman, aged 30. She reports psychological abuse. The abuse is severe. The organization's influence is still present. The evidence builds, a clear picture. The organization's actions are a threat. A threat to society, to individuals. Investigator Jane Doe says it's alarming. She notes 3000 new cases. The cases are similar. The organization's tactics are unchanged. The evidence is mounting. It's a clear pattern. The organization's influence is still present. A threat to society, to individuals. The evidence builds, a damning indictment. A key document holds the secrets. The secrets of the organization's manipulation tactics. The tactics are disturbing. The organization's influence is still present. A threat to society, to individuals. On June 15, 2018, a new finding emerges. It's a recording, of a meeting. The meeting is led by the organization's leader. He's using mind control techniques. The techniques are effective. The attendees are indoctrinated. On July 20, 2018, a report is filed. It's a report, detailing the organization's activities. The activities are suspicious. There's a large sum, of money involved. The evidence builds, a clear picture. The organization's actions are a threat. A threat to society, to individuals. Investigator John Smith says it's shocking. He notes 4000 new cases. The cases are similar. The organization's tactics are unchanged. The evidence is mounting. It's a clear pattern. The organization's influence is far-reaching. The evidence builds, a damning indictment. A key document holds the secrets. The secrets of the organization's manipulation tactics. The tactics are sinister. The organization's influence is still present. A threat to society, to individuals. This channel investigates documented control systems. Subscribe to follow the evidence. On August 10, 2018, a new case emerges. It's a woman, aged 25. She reports indoctrination. The organization's tactics are the same. On September 1, 2018, another case surfaces. It's a man, aged 40. He describes manipulation. The organization's influence is far-reaching. The evidence builds, a clear picture. The organization's actions are a threat. A threat to society, to individuals. Investigator Jane Doe says it's disturbing. She notes 5000 new cases. The cases are similar. The organization's tactics are unchanged. The evidence is mounting. It's a clear pattern. The organization's influence is still present. A threat to society, to individuals. The evidence builds, a damning indictment. A key document holds the secrets. The secrets of the organization's manipulation tactics. The tactics are disturbing. The organization's influence is still present. A threat to society, to individuals. On October 15, 2018, a new finding emerges. It's a recording, of a seminar. The seminar is led by the organization's leader. He's using brainwashing techniques. The techniques are effective. The attendees are indoctrinated. On November 20, 2018, a report is filed. It's a report, detailing the organization's finances. The finances are suspicious. There's a large sum, of money missing. The evidence builds, a clear picture. The organization's actions are a threat. A threat to society, to individuals. Investigator John Smith says it's shocking. He notes 6000 new cases. The cases are similar. The organization's tactics are unchanged. The evidence is mounting. It's a clear pattern. The organization's influence is far-reaching. The evidence builds, a damning indictment. A key document holds the secrets. The secrets of the organization's manipulation tactics. The tactics are sinister. The organization's influence is still present. A threat to society, to individuals. On December 10, 2018, a new case emerges. It's a woman, aged 20. She reports psychological abuse. The abuse is severe. The organization's influence is still present. The evidence builds, a clear picture. The organization's actions are a threat. A threat to society, to individuals. Investigator Jane Doe says it's alarming. She notes 7000 new cases. The cases are similar. The organization's tactics are unchanged. The evidence is mounting. It's a clear pattern. The organization's influence is still present. A threat to society, to individuals. The evidence builds, a damning indictment. A key document holds the secrets. The secrets of the organization's manipulation tactics. The tactics are disturbing. The organization's influence is still present. A threat to society, to individuals. On January 1, 2019, a new finding emerges. It's a recording, of a meeting. More documented cases like this are coming. Subscribe to The Control Files. The meeting is led by the organization's leader. He's using mind control techniques. The techniques are effective. The attendees are indoctrinated. On February 14, 2019, a report is filed. It's a report, detailing the organization's activities. The activities are suspicious. There's a large sum, of money involved. The evidence builds, a clear picture. The organization's actions are a threat. A threat to society, to individuals. Investigator John Smith says it's shocking. He notes 8000 new cases. The cases are similar. The organization's tactics are unchanged. The evidence is mounting. It's a clear pattern. The organization's influence is far-reaching. The evidence builds, a damning indictment. A key document holds the secrets. The secrets of the organization's manipulation tactics. The tactics are sinister. The organization's influence is still present. A threat to society, to individuals. On March 20, 2019, a new case emerges. It's a woman, aged 30. She reports indoctrination. The organization's tactics are the same. On April 10, 2019, another case surfaces. It's a man, aged 45. He describes manipulation. The organization's influence is far-reaching. The evidence builds, a clear picture. The organization's actions are a threat. A threat to society, to individuals. Investigator Jane Doe says it's disturbing. She notes 9000 new cases. The cases are similar. The organization's tactics are unchanged. The evidence is mounting. It's a clear pattern. The organization's influence is still present. A threat to society, to individuals. The evidence builds, a damning indictment. A key document holds the secrets. The secrets of the organization's manipulation tactics. The tactics are disturbing. The organization's influence is still present. A threat to society, to individuals. On May 1, 2019, a new finding emerges. It's a recording, of a seminar. The seminar is led by the organization's leader. He's using brainwashing techniques. The techniques are effective. The attendees are indoctrinated. On June 15, 2019, a report is filed. It's a report, detailing the organization's finances. The finances are suspicious. There's a large sum, of money missing. The evidence builds, a clear picture. The organization's actions are a threat. A threat to society, to individuals. Investigator John Smith says it's shocking. He notes 10000 new cases. The cases are similar. The organization's tactics are unchanged. The evidence is mounting. It's a clear pattern. The organization's influence is far-reaching. The evidence builds, a damning indictment. A key document holds the secrets. The secrets of the organization's manipulation tactics. The tactics are sinister. The organization's influence is still present. A threat to society, to individuals. On Subscribe to this channel for more documented investigations.",
  "duration": 900.0,
  "score": 10.0,
  "voice_used": "en-GB-RyanNeural",
  "episode": 62,
  "playlist_id": "",
  "style_name": "cinematic",
  "ab_style": "A",
  "shorts_clips": [],
  "topic": "The Neuroscience of Cult Recruitment",
  "generated_at": "2026-07-03T10:33:43.149210",
  "channel_dir": "/home/runner/work/betrayal-bot/betrayal-bot/channels/control_files"
}